tests/__init__.py
tests/backend/__init__.py
tests/backend/resources.py
tests/backend/counts/__init__.py
tests/backend/counts/test_count_arabic_long_words.py
tests/backend/counts/test_count_arabic_syllables.py
tests/backend/counts/test_count_chars.py
tests/backend/counts/test_count_complex_arabic_words.py
tests/backend/counts/test_count_difficult_words.py
tests/backend/counts/test_count_faseeh.py
tests/backend/counts/test_count_letters.py
tests/backend/counts/test_count_long_words.py
tests/backend/counts/test_count_miniwords.py
tests/backend/counts/test_count_monosyllable_words.py
tests/backend/counts/test_count_polysyllable_words.py
tests/backend/counts/test_count_sentences.py
tests/backend/counts/test_count_syllables.py
tests/backend/counts/test_count_words.py
tests/backend/metrics/__init__.py
tests/backend/metrics/test_automated_readability_index.py
tests/backend/metrics/test_chars_per_word.py
tests/backend/metrics/test_coleman_liau_index.py
tests/backend/metrics/test_crawford.py
tests/backend/metrics/test_dale_chall_readability_score.py
tests/backend/metrics/test_dale_chall_readability_score_v2.py
tests/backend/metrics/test_fernandez_huerta.py
tests/backend/metrics/test_flesch_kincaid_grade.py
tests/backend/metrics/test_flesch_reading_ease.py
tests/backend/metrics/test_gulpease_index.py
tests/backend/metrics/test_gunning_fog.py
tests/backend/metrics/test_gutierrez_polini.py
tests/backend/metrics/test_letters_per_word.py
tests/backend/metrics/test_linsear_write_formula.py
tests/backend/metrics/test_lix.py
tests/backend/metrics/test_osman.py
tests/backend/metrics/test_reading_time.py
tests/backend/metrics/test_rix.py
tests/backend/metrics/test_sentences_per_word.py
tests/backend/metrics/test_smog_index.py
tests/backend/metrics/test_spache_readability.py
tests/backend/metrics/test_syllables_per_word.py
tests/backend/metrics/test_szigriszt_pazos.py
tests/backend/metrics/test_text_standard.py
tests/backend/metrics/test_wiener_sachtextformel.py
textstat-0.7.9.dist-info/licenses/LICENSE
textstat-0.7.9.dist-info/METADATA
textstat-0.7.9.dist-info/WHEEL
textstat-0.7.9.dist-info/top_level.txt
textstat-0.7.9.dist-info/RECORD
